my_xch4nges/__init__.py
my_xch4nges/binance.py
my_xch4nges/bitget.py
my_xch4nges/bithumb.py
my_xch4nges/bybit.py
my_xch4nges/gateio.py
my_xch4nges/huobi.py
my_xch4nges/mexc.py
my_xch4nges/okx.py
my_xch4nges/upbit.py
my_xch4nges-1.1.dist-info/LICENSE
my_xch4nges-1.1.dist-info/METADATA
my_xch4nges-1.1.dist-info/WHEEL
my_xch4nges-1.1.dist-info/top_level.txt
my_xch4nges-1.1.dist-info/RECORD
