Metadata-Version: 2.1
Name: my-xch4nges
Version: 1.1
Summary: Comprehensive list of exchange api implements to use on my projects.
Home-page: UNKNOWN
Author: bemodest.eth
License: UNKNOWN
Platform: UNKNOWN
Classifier: Programming Language :: Python :: 3
Classifier: License :: OSI Approved :: MIT License
License-File: LICENSE
Requires-Dist: gate-api
Requires-Dist: pybithumb
Requires-Dist: pyokx
Requires-Dist: python-dotenv
Requires-Dist: python-bitget
Requires-Dist: pyupbit
